saltext/mysql/__init__.py
saltext/mysql/version.py
saltext/mysql/auth/__init__.py
saltext/mysql/auth/mysql.py
saltext/mysql/cache/__init__.py
saltext/mysql/cache/mysql_cache.py
saltext/mysql/modules/__init__.py
saltext/mysql/modules/mysql.py
saltext/mysql/pillar/__init__.py
saltext/mysql/pillar/mysql.py
saltext/mysql/returners/__init__.py
saltext/mysql/returners/mysql.py
saltext/mysql/states/__init__.py
saltext/mysql/states/mysql_database.py
saltext/mysql/states/mysql_grants.py
saltext/mysql/states/mysql_query.py
saltext/mysql/states/mysql_user.py
saltext.mysql-1.1.0.dist-info/LICENSE
saltext.mysql-1.1.0.dist-info/METADATA
saltext.mysql-1.1.0.dist-info/NOTICE
saltext.mysql-1.1.0.dist-info/WHEEL
saltext.mysql-1.1.0.dist-info/entry_points.txt
saltext.mysql-1.1.0.dist-info/top_level.txt
saltext.mysql-1.1.0.dist-info/RECORD
